nlweb_retrieval/__init__.py
nlweb_retrieval/azure_search_client.py
nlweb_retrieval/bing_search_client.py
nlweb_retrieval/cf_autorag_client.py
nlweb_retrieval/elasticsearch_client.py
nlweb_retrieval/milvus_client.py
nlweb_retrieval/opensearch_client.py
nlweb_retrieval/postgres_client.py
nlweb_retrieval/qdrant.py
nlweb_retrieval/qdrant_retrieve.py
nlweb_retrieval/shopify_mcp.py
nlweb_retrieval/snowflake_client.py
nlweb_retrieval/utils/snowflake.py
nlweb_retrieval-0.5.6.dist-info/METADATA
nlweb_retrieval-0.5.6.dist-info/WHEEL
nlweb_retrieval-0.5.6.dist-info/top_level.txt
nlweb_retrieval-0.5.6.dist-info/RECORD
