Metadata-Version: 2.4
Name: nlweb-retrieval
Version: 0.5.6
Summary: Retrieval bundle for NLWeb - includes vector database clients for multiple providers
Author: Microsoft Corporation
License: MIT
Project-URL: Homepage, https://github.com/microsoft/NLWeb_Core
Project-URL: Repository, https://github.com/microsoft/NLWeb_Core
Project-URL: Issues, https://github.com/microsoft/NLWeb_Core/issues
Classifier: Development Status :: 4 - Beta
Classifier: Intended Audience :: Developers
Classifier: License :: OSI Approved :: MIT License
Classifier: Programming Language :: Python :: 3
Classifier: Programming Language :: Python :: 3.9
Classifier: Programming Language :: Python :: 3.10
Classifier: Programming Language :: Python :: 3.11
Classifier: Programming Language :: Python :: 3.12
Requires-Python: >=3.9
Requires-Dist: nlweb-core>=0.5.5
Requires-Dist: azure-core
Requires-Dist: azure-search-documents>=11.4.0
Requires-Dist: azure-identity>=1.12.0
Requires-Dist: pymilvus>=1.1.0
Requires-Dist: numpy
Requires-Dist: httpx>=0.28.1
Requires-Dist: qdrant-client>=1.14.0
Requires-Dist: elasticsearch[async]<9,>=8
Requires-Dist: psycopg[binary]>=3.1.12
Requires-Dist: psycopg[pool]>=3.2.0
Requires-Dist: pgvector>=0.4.0
Requires-Dist: aiohttp>=3.8.0
Requires-Dist: cloudflare>=4.3.1
Requires-Dist: zon>=3.0.0
Requires-Dist: markdown>=3.8.2
Requires-Dist: beautifulsoup4>=4.13.4
Provides-Extra: dev
Requires-Dist: pytest>=7.0; extra == "dev"
Requires-Dist: pytest-asyncio>=0.21.0; extra == "dev"
